Metadata-Version: 2.1
Name: Mensajes-Wilmar
Version: 4.0
Summary: Paquete que muestra mensajes de saludos y despedidas
Home-page: https://www.instagram.com/wilmargalvis/
Author: Wilmar Galvis
Author-email: wagalvis24@gmail.com
Classifier: Environment :: Console
Classifier: Intended Audience :: Developers
Classifier: License :: OSI Approved :: MIT License
Classifier: Operating System :: OS Independent
Classifier: Programming Language :: Python
Classifier: Programming Language :: Python :: 3.9
Classifier: Programming Language :: Python :: 3.10
Classifier: Programming Language :: Python :: 3.11
Classifier: Topic :: Utilities
License-File: LICENSE
Requires-Dist: numpy (>=1.24.2)
